gridlight/__init__.py
gridlight/_util.py
gridlight/constants.py
gridlight/electrificationfilter.py
gridlight/gridlight.py
gridlight/metrics.py
gridlight/post.py
gridlight/prepare.py
gridlight/util/__init__.py
gridlight/util/loading.py
gridlight/util/raster.py
gridlight/util/remote_storage.py
gridlight/util/viirs.py
vida_gridlight-0.1.0.dist-info/LICENSE
vida_gridlight-0.1.0.dist-info/METADATA
vida_gridlight-0.1.0.dist-info/WHEEL
vida_gridlight-0.1.0.dist-info/RECORD
