Metadata-Version: 2.1
Name: vida-gridlight
Version: 0.1.0
Summary: A package to predict electrification status of settlements and MV power line predictions using NASA VIIRS nightlight imagery.
License: MIT
Requires-Python: >=3.8,<3.12
Classifier: License :: OSI Approved :: MIT License
Classifier: Programming Language :: Python :: 3
Classifier: Programming Language :: Python :: 3.8
Classifier: Programming Language :: Python :: 3.9
Classifier: Programming Language :: Python :: 3.10
Classifier: Programming Language :: Python :: 3.11
Requires-Dist: accsr (==0.3.4)
Requires-Dist: beautifulsoup4 (>=4.12.2,<5.0.0)
Requires-Dist: geopandas (>=0.13.0,<0.14.0)
Requires-Dist: python-keycloak (>=2.16.2,<3.0.0)
Requires-Dist: rasterio (>=1.3.6,<2.0.0)
Requires-Dist: scikit-image (>=0.20.0,<0.21.0)
Requires-Dist: scikit-learn (>=1.2.2,<2.0.0)
Requires-Dist: shapely (>=2.0.1,<3.0.0)
